scian_ciiu/__init__.py
scian_ciiu/src/__init__.py
scian_ciiu/src/data.py
scian_ciiu/src/scian_ciiu.py
scian_ciiu/src/search.py
scian_ciiu/test/__init__.py
scian_ciiu/test/test_scian_ciiu.py
scian_ciiu-0.0.13.dist-info/LICENCE
scian_ciiu-0.0.13.dist-info/METADATA
scian_ciiu-0.0.13.dist-info/WHEEL
scian_ciiu-0.0.13.dist-info/top_level.txt
scian_ciiu-0.0.13.dist-info/RECORD
