Metadata-Version: 2.1
Name: scian-ciiu
Version: 0.0.13
Summary: A library to search the corresponding mexican scian or ciiu given an input parameter
Home-page: https://github.com/dimitrj89/scian_ciiu
Author: Dimitrj Bonansea
Author-email: dimitrj22@gmail.com
License: MIT
Platform: UNKNOWN
Classifier: License :: OSI Approved :: MIT License
Classifier: Programming Language :: Python :: 3.10
Classifier: Operating System :: OS Independent
Requires-Python: >=3.10
License-File: LICENCE
Provides-Extra: dev
Requires-Dist: pytest >=7.0 ; extra == 'dev'
Requires-Dist: twine >=4.0.2 ; extra == 'dev'
